experi/__init__.py
experi/pbs.py
experi/run.py
experi/version.py
experi-0.2.2.dist-info/DESCRIPTION.rst
experi-0.2.2.dist-info/METADATA
experi-0.2.2.dist-info/RECORD
experi-0.2.2.dist-info/WHEEL
experi-0.2.2.dist-info/entry_points.txt
experi-0.2.2.dist-info/metadata.json
experi-0.2.2.dist-info/top_level.txt
