Metadata-Version: 2.0
Name: experi
Version: 0.2.2
Summary: UNKNOWN
Home-page: UNKNOWN
Author: Malcolm Ramsay
Author-email: malramsay64@gmail.com
License: UNKNOWN
Platform: UNKNOWN
Classifier: Development Status :: 3 - Alpha
Classifier: Environment :: Console
Classifier: Intended Audience :: Developers
Classifier: Intended Audience :: Science/Research
Classifier: License :: OSI Approved :: MIT License
Classifier: Operating System :: MacOS :: MacOS X
Classifier: Operating System :: POSIX :: Linux
Classifier: Programming Language :: Python :: 3
Classifier: Programming Language :: Python :: 3.6
Requires-Python: >=3.4
Requires-Dist: click
Requires-Dist: ruamel.yaml
Requires-Dist: typing
